LICENSE
MANIFEST.in
README.md
pyproject.toml
setup.cfg
setup.py
src/python_socketio_fork.egg-info/PKG-INFO
src/python_socketio_fork.egg-info/SOURCES.txt
src/python_socketio_fork.egg-info/dependency_links.txt
src/python_socketio_fork.egg-info/not-zip-safe
src/python_socketio_fork.egg-info/requires.txt
src/python_socketio_fork.egg-info/top_level.txt
src/socketio/__init__.py
src/socketio/asgi.py
src/socketio/asyncio_aiopika_manager.py
src/socketio/asyncio_client.py
src/socketio/asyncio_manager.py
src/socketio/asyncio_namespace.py
src/socketio/asyncio_pubsub_manager.py
src/socketio/asyncio_redis_manager.py
src/socketio/asyncio_server.py
src/socketio/base_manager.py
src/socketio/client.py
src/socketio/exceptions.py
src/socketio/kafka_manager.py
src/socketio/kombu_manager.py
src/socketio/middleware.py
src/socketio/msgpack_packet.py
src/socketio/namespace.py
src/socketio/packet.py
src/socketio/pubsub_manager.py
src/socketio/redis_manager.py
src/socketio/server.py
src/socketio/tornado.py
src/socketio/zmq_manager.py