Metadata-Version: 2.1
Name: python-socketio-fork
Version: 5.8.1
Summary: Fork of Socket.IO server and client for Python
Home-page: https://github.com/miguelgrinberg/python-socketio
Author: fangte
Author-email: 416189496@qq.com
License: UNKNOWN
Project-URL: Bug Tracker, https://github.com/miguelgrinberg/python-socketio/issues
Platform: UNKNOWN
Classifier: Environment :: Web Environment
Classifier: Intended Audience :: Developers
Classifier: Programming Language :: Python :: 3
Classifier: License :: OSI Approved :: MIT License
Classifier: Operating System :: OS Independent
Requires-Python: >=3.6
Provides-Extra: client
Provides-Extra: asyncio_client
